flashcardz.py
flashcardz-0.8.0.dist-info/licenses/LICENSE.txt
flashcardz-0.8.0.dist-info/METADATA
flashcardz-0.8.0.dist-info/WHEEL
flashcardz-0.8.0.dist-info/top_level.txt
flashcardz-0.8.0.dist-info/RECORD
