Metadata-Version: 2.4
Name: flashcardz
Version: 0.8.0
Summary: flash cards for language learners
Author-email: Ken Carlton <kencarlton55@gmail.com>
Maintainer-email: Ken Carlton <kencarlton55@gmail.com>
License: GPLv3+
Project-URL: Homepage, https://github.com/kcarlton55/flashcardz
Project-URL: Tutorial, https://github.com/kcarlton55/flashcardz
Keywords: flash,cards,language
Classifier: Programming Language :: Python :: 3
Classifier: Development Status :: 4 - Beta
Classifier: Natural Language :: English
Classifier: License :: OSI Approved :: GNU General Public License v3 (GPLv3)
Classifier: Intended Audience :: Education
Classifier: Intended Audience :: End Users/Desktop
Classifier: Operating System :: OS Independent
Requires-Python: >=3.8
License-File: LICENSE.txt
Dynamic: license-file
